{
  "survey": {
    "id": "1a2b3c4d",
    "name": "Satisfaction Survey",
    "row_version": 1620734400000
  },
  "sections": [
    {
      "id": "5e6f7g8h",
      "order": 1,
      "name": "Customer Satisfaction",
      "survey_id": "1a2b3c4d",
      "visibility": 0,
      "row_version": 1620734700000,
      "questions": [
        {
          "id": "9i0j1k2l",
          "order": 1,
          "content": "How satisfied are you with our product?",
          "section_id": "5e6f7g8h",
          "question_type": 0,
          "required": true,
          "row_version": 1620735000000,
          "options": [
            {
              "id": "3m4n5o6p",
              "order": 1,
              "question_id": "9i0j1k2l",
              "label": "Very Satisfied",
              "row_version": 1620735300000
            },
            {
              "id": "7q8r9s0t",
              "order": 2,
              "question_id": "9i0j1k2l",
              "label": "Satisfied",
              "row_version": 1620735600000
            },
            {
              "id": "1u2v3w4x",
              "order": 3,
              "question_id": "9i0j1k2l",
              "label": "Neutral",
              "row_version": 1620735900000
            },
            {
              "id": "5y6z7a8b",
              "order": 4,
              "question_id": "9i0j1k2l",
              "label": "Dissatisfied",
              "row_version": 1620736200000
            },
            {
              "id": "9c0d1e2f",
              "order": 5,
              "question_id": "9i0j1k2l",
              "label": "Very Dissatisfied",
              "row_version": 1620736500000
            }
          ]
        },
        {
          "id": "9i0j1k2l",
          "order": 2,
          "content": "How satisfied are you with our product?",
          "section_id": "5e6f7g8h",
          "question_type": 0,
          "required": true,
          "row_version": 1620735000000,
          "options": [
            {
              "id": "3m4n5o6p",
              "order": 1,
              "question_id": "9i0j1k2l",
              "label": "Very Happy",
              "row_version": 1620735300000
            },
            {
              "id": "7q8r9s0t",
              "order": 2,
              "question_id": "9i0j1k2l",
              "label": "Happy",
              "row_version": 1620735600000
            },
            {
              "id": "1u2v3w4x",
              "order": 3,
              "question_id": "9i0j1k2l",
              "label": "Neutral",
              "row_version": 1620735900000
            },
            {
              "id": "5y6z7a8b",
              "order": 4,
              "question_id": "9i0j1k2l",
              "label": "Unhappy",
              "row_version": 1620736200000
            },
            {
              "id": "9c0d1e2f",
              "order": 5,
              "question_id": "9i0j1k2l",
              "label": "Very Unhappy",
              "row_version": 1620736500000
            }
          ]
        }
      ]
    },
    {
      "id": "5e6f7g8h",
      "order": 2,
      "name": "Customer Satisfaction",
      "survey_id": "1a2b3c4d",
      "visibility": 0,
      "row_version": 1620734700000,
      "questions": [
        {
          "id": "9i0j1k2l",
          "order": 1,
          "content": "How satisfied are you with our product?",
          "section_id": "5e6f7g8h",
          "question_type": 0,
          "required": true,
          "row_version": 1620735000000,
          "options": [
            {
              "id": "3m4n5o6p",
              "order": 1,
              "question_id": "9i0j1k2l",
              "label": "Very Satisfied",
              "row_version": 1620735300000
            },
            {
              "id": "7q8r9s0t",
              "order": 2,
              "question_id": "9i0j1k2l",
              "label": "Satisfied",
              "row_version": 1620735600000
            },
            {
              "id": "1u2v3w4x",
              "order": 3,
              "question_id": "9i0j1k2l",
              "label": "Neutral",
              "row_version": 1620735900000
            },
            {
              "id": "5y6z7a8b",
              "order": 4,
              "question_id": "9i0j1k2l",
              "label": "Dissatisfied",
              "row_version": 1620736200000
            },
            {
              "id": "9c0d1e2f",
              "order": 5,
              "question_id": "9i0j1k2l",
              "label": "Very Dissatisfied",
              "row_version": 1620736500000
            }
          ]
        }
      ]
    }
  ]
}